traffic/__init__.py
traffic/alert.py
traffic/api.py
traffic/camera.py
traffic/direction.py
traffic/event.py
traffic/roadway.py
traffic/sign.py
traffic/weather.py
nysdotapi-1.0.1.dist-info/LICENSE
nysdotapi-1.0.1.dist-info/METADATA
nysdotapi-1.0.1.dist-info/WHEEL
nysdotapi-1.0.1.dist-info/top_level.txt
nysdotapi-1.0.1.dist-info/RECORD
