Metadata-Version: 2.1
Name: nysdotapi
Version: 1.0.1
Summary: NYS DOT Traffic Camera Python API
Home-page: https://github.com/ryanrudes/traffic
Author: Ryan Rudes
Author-email: ryanrudes@gmail.com
License: MIT
Keywords: ny,traffic,live,stream,feed,camera,road,street
Classifier: Development Status :: 5 - Production/Stable
Classifier: Intended Audience :: Developers
Classifier: Intended Audience :: Information Technology
Classifier: Intended Audience :: Science/Research
Classifier: Natural Language :: English
Classifier: Topic :: Database
Classifier: Topic :: Multimedia :: Video
Classifier: Topic :: Scientific/Engineering :: Image Processing
Classifier: Topic :: Scientific/Engineering :: Image Recognition
Classifier: Topic :: Scientific/Engineering :: Information Analysis
Classifier: Topic :: Software Development :: Libraries :: Python Modules
Classifier: License :: OSI Approved :: MIT License
Classifier: Programming Language :: Python :: 3.6
Classifier: Programming Language :: Python :: 3.7
Classifier: Programming Language :: Python :: 3.8
Classifier: Programming Language :: Python :: 3.9
Classifier: Programming Language :: Python :: 3.10
Classifier: Programming Language :: Python :: 3.11
Classifier: Programming Language :: Python :: 3.12
Classifier: Programming Language :: Python :: 3.13
License-File: LICENSE
Requires-Dist: pillow
Requires-Dist: numpy
Requires-Dist: opencv-python
